tddlspserver/__init__.py
tddlspserver/__main__.py
tddlspserver/server.py
tddlspserver/cst/__init__.py
tddlspserver/cst/calculate_complexity_visitor.py
tddlspserver/cst/cmake_file_generator_visitor.py
tddlspserver/cst/diagnostic_listener.py
tddlspserver/cst/f90_file_generator_visitor.py
tddlspserver/cst/pf_file_generator_visitor.py
tddlspserver/cst/symbol_table_visitor.py
tddlspserver/cst/system_file_visitor.py
tddlspserver/filewriter/__init__.py
tddlspserver/filewriter/file_writer.py
tddlspserver/filewriter/jinjatemplates/__init__.py
tddlspserver/fxca/model/__init__.py
tddlspserver/fxca/model/common_block.py
tddlspserver/fxca/model/containment_hash_map.py
tddlspserver/fxca/model/e_direction.py
tddlspserver/fxca/model/fortran_module.py
tddlspserver/fxca/model/fortran_operation.py
tddlspserver/fxca/model/fortran_parameter.py
tddlspserver/fxca/model/fortran_project.py
tddlspserver/fxca/model/fortran_variable.py
tddlspserver/fxca/model/fxca_model.py
tddlspserver/fxca/util/fxtran_utils.py
tddlspserver/fxca/util/node_utils.py
tddlspserver/gen/python/TestSuite/TestSuiteLexer.py
tddlspserver/gen/python/TestSuite/TestSuiteListener.py
tddlspserver/gen/python/TestSuite/TestSuiteParser.py
tddlspserver/gen/python/TestSuite/TestSuiteVisitor.py
tddlspserver/symboltable/__init__.py
tddlspserver/symboltable/symbol_table.py
tddlspserver/utils/__init__.py
tddlspserver/utils/calculate_complexity.py
tddlspserver/utils/compute_token_index.py
tddlspserver/utils/suggest_variables.py
tddlspserver/utils/tdd_errors_strategy.py
TDD_Language-0.80.0.dist-info/LICENSE.txt
TDD_Language-0.80.0.dist-info/METADATA
TDD_Language-0.80.0.dist-info/WHEEL
TDD_Language-0.80.0.dist-info/entry_points.txt
TDD_Language-0.80.0.dist-info/top_level.txt
TDD_Language-0.80.0.dist-info/RECORD
