Metadata-Version: 2.1
Name: TDD-Language
Version: 0.80.0
Summary: A program for a language server based on the test driven development ocean-dsl.
Author-email: sgu <sgu@informatik.uni-kiel.de>
License: Apache License (2.0)
Project-URL: oceandsl · GitLab, https://git.se.informatik.uni-kiel.de/oceandsl
Project-URL: OceanDSL · GitHub, https://github.com/cau-se/python-oceandsls
Classifier: Development Status :: 3 - Alpha
Classifier: Programming Language :: Python :: 3.10
Classifier: Intended Audience :: Developers
Classifier: License :: OSI Approved :: Apache Software License
Classifier: Operating System :: OS Independent
Classifier: Topic :: Software Development :: Testing
Requires-Python: >=3.10
License-File: LICENSE.txt
Requires-Dist: odsllib >=0.38
